feed/__init__.py
feed/actionchains.py
feed/actiontypes.py
feed/authnclient.py
feed/chainsessions.py
feed/crawling.py
feed/engine.py
feed/logger.py
feed/service.py
feed/settings.py
feed/test_actionchains.py
feed/test_authnclient.py
feed/test_crawling.py
feed/test_testutils.py
feed/testinterfaces.py
feed/testutils.py
feed_utils-0.7.5.dist-info/METADATA
feed_utils-0.7.5.dist-info/WHEEL
feed_utils-0.7.5.dist-info/top_level.txt
feed_utils-0.7.5.dist-info/RECORD
